{
  "version": "1.0.0",
  "name": "Jingle Bells Rock",
  "bpm": 140,
  "globalSteps": 64,
  "createdAt": "2026-01-01T00:00:00.000Z",
  "tracks": [
    {
      "id": "jb-guitar",
      "name": "Guitare Électrique",
      "color": "#ef4444",
      "instrument": "Guitare Électrique",
      "steps": [false,false,false,false,false,false,false,false,false,false,false,false,false,false,false,false,false,false,false,false,false,false,false,false,false,false,false,false,false,false,false,false,false,false,false,false,false,false,false,false,false,false,false,false,false,false,false,false,false,false,false,false,false,false,false,false,false,false,false,false,false,false,false,false],
      "pianoSteps": [
        {"active":true,"note":"E4"},{"active":false,"note":""},
        {"active":true,"note":"E4"},{"active":false,"note":""},
        {"active":true,"note":"E4"},{"active":false,"note":""},
        {"active":false,"note":""},{"active":false,"note":""},
        {"active":true,"note":"E4"},{"active":false,"note":""},
        {"active":true,"note":"E4"},{"active":false,"note":""},
        {"active":true,"note":"E4"},{"active":false,"note":""},
        {"active":false,"note":""},{"active":false,"note":""},
        {"active":true,"note":"E4"},{"active":false,"note":""},
        {"active":true,"note":"G4"},{"active":false,"note":""},
        {"active":true,"note":"C4"},{"active":false,"note":""},
        {"active":true,"note":"D4"},{"active":false,"note":""},
        {"active":true,"note":"E4"},{"active":false,"note":""},
        {"active":false,"note":""},{"active":false,"note":""},
        {"active":false,"note":""},{"active":false,"note":""},
        {"active":false,"note":""},{"active":false,"note":""},
        {"active":true,"note":"F4"},{"active":false,"note":""},
        {"active":true,"note":"F4"},{"active":false,"note":""},
        {"active":true,"note":"F4"},{"active":false,"note":""},
        {"active":true,"note":"F4"},{"active":false,"note":""},
        {"active":true,"note":"F4"},{"active":false,"note":""},
        {"active":true,"note":"E4"},{"active":false,"note":""},
        {"active":true,"note":"E4"},{"active":false,"note":""},
        {"active":false,"note":""},{"active":false,"note":""},
        {"active":true,"note":"E4"},{"active":false,"note":""},
        {"active":true,"note":"D4"},{"active":false,"note":""},
        {"active":true,"note":"D4"},{"active":false,"note":""},
        {"active":true,"note":"E4"},{"active":false,"note":""},
        {"active":true,"note":"D4"},{"active":false,"note":""},
        {"active":false,"note":""},{"active":false,"note":""},
        {"active":true,"note":"G4"},{"active":false,"note":""},
        {"active":false,"note":""},{"active":false,"note":""}
      ],
      "length": 64,
      "volume": 85,
      "pan": 0,
      "muted": false,
      "soloed": false,
      "fx": {
        "reverb": {"enabled": true, "wet": 0.25},
        "delay":  {"enabled": true, "wet": 0.2},
        "distortion": {"enabled": true, "wet": 0.45},
        "filter": {"enabled": false, "frequency": 1000, "type": "lowpass"}
      }
    },
    {
      "id": "jb-bass",
      "name": "Basse Rock",
      "color": "#f59e0b",
      "instrument": "Bass Synth",
      "steps": [false,false,false,false,false,false,false,false,false,false,false,false,false,false,false,false,false,false,false,false,false,false,false,false,false,false,false,false,false,false,false,false,false,false,false,false,false,false,false,false,false,false,false,false,false,false,false,false,false,false,false,false,false,false,false,false,false,false,false,false,false,false,false,false],
      "pianoSteps": [
        {"active":true,"note":"E2"},{"active":false,"note":""},{"active":false,"note":""},{"active":false,"note":""},
        {"active":true,"note":"E2"},{"active":false,"note":""},{"active":false,"note":""},{"active":false,"note":""},
        {"active":true,"note":"E2"},{"active":false,"note":""},{"active":false,"note":""},{"active":false,"note":""},
        {"active":true,"note":"E2"},{"active":false,"note":""},{"active":false,"note":""},{"active":false,"note":""},
        {"active":true,"note":"C2"},{"active":false,"note":""},{"active":false,"note":""},{"active":false,"note":""},
        {"active":true,"note":"C2"},{"active":false,"note":""},{"active":false,"note":""},{"active":false,"note":""},
        {"active":true,"note":"C2"},{"active":false,"note":""},{"active":false,"note":""},{"active":false,"note":""},
        {"active":true,"note":"C2"},{"active":false,"note":""},{"active":false,"note":""},{"active":false,"note":""},
        {"active":true,"note":"F2"},{"active":false,"note":""},{"active":false,"note":""},{"active":false,"note":""},
        {"active":true,"note":"F2"},{"active":false,"note":""},{"active":false,"note":""},{"active":false,"note":""},
        {"active":true,"note":"F2"},{"active":false,"note":""},{"active":false,"note":""},{"active":false,"note":""},
        {"active":true,"note":"F2"},{"active":false,"note":""},{"active":false,"note":""},{"active":false,"note":""},
        {"active":true,"note":"G2"},{"active":false,"note":""},{"active":false,"note":""},{"active":false,"note":""},
        {"active":true,"note":"G2"},{"active":false,"note":""},{"active":false,"note":""},{"active":false,"note":""},
        {"active":true,"note":"G2"},{"active":false,"note":""},{"active":false,"note":""},{"active":false,"note":""},
        {"active":true,"note":"E2"},{"active":false,"note":""},{"active":false,"note":""},{"active":false,"note":""}
      ],
      "length": 64,
      "volume": 78,
      "pan": 0,
      "muted": false,
      "soloed": false,
      "fx": {
        "reverb": {"enabled": false, "wet": 0.2},
        "delay":  {"enabled": false, "wet": 0.2},
        "distortion": {"enabled": true, "wet": 0.2},
        "filter": {"enabled": true, "frequency": 500, "type": "lowpass"}
      }
    },
    {
      "id": "jb-kick",
      "name": "Kick Rock",
      "color": "#dc2626",
      "instrument": "Kick",
      "steps": [
        true,false,false,false,true,false,false,false,
        true,false,false,false,true,false,false,false,
        true,false,false,false,true,false,false,false,
        true,false,false,false,true,false,false,false,
        true,false,false,false,true,false,false,false,
        true,false,false,false,true,false,false,false,
        true,false,false,false,true,false,false,false,
        true,false,false,false,true,false,false,false
      ],
      "length": 64,
      "volume": 88,
      "pan": 0,
      "muted": false,
      "soloed": false,
      "fx": {
        "reverb": {"enabled": false, "wet": 0.2},
        "delay":  {"enabled": false, "wet": 0.2},
        "distortion": {"enabled": false, "wet": 0.0},
        "filter": {"enabled": false, "frequency": 1000, "type": "lowpass"}
      }
    },
    {
      "id": "jb-snare",
      "name": "Snare Rock",
      "color": "#22c55e",
      "instrument": "Snare",
      "steps": [
        false,false,false,false,true,false,false,false,
        false,false,false,false,true,false,false,false,
        false,false,false,false,true,false,false,false,
        false,false,false,false,true,false,false,false,
        false,false,false,false,true,false,false,false,
        false,false,false,false,true,false,false,false,
        false,false,false,false,true,false,false,false,
        false,false,false,false,true,false,false,false
      ],
      "length": 64,
      "volume": 82,
      "pan": 0,
      "muted": false,
      "soloed": false,
      "fx": {
        "reverb": {"enabled": true, "wet": 0.3},
        "delay":  {"enabled": false, "wet": 0.2},
        "distortion": {"enabled": false, "wet": 0.0},
        "filter": {"enabled": false, "frequency": 1000, "type": "lowpass"}
      }
    },
    {
      "id": "jb-hihat",
      "name": "HiHat Rock",
      "color": "#06b6d4",
      "instrument": "HiHat",
      "steps": [
        true,false,true,false,true,false,true,false,
        true,false,true,false,true,false,true,false,
        true,false,true,false,true,false,true,false,
        true,false,true,false,true,false,true,false,
        true,false,true,false,true,false,true,false,
        true,false,true,false,true,false,true,false,
        true,false,true,false,true,false,true,false,
        true,false,true,false,true,false,true,false
      ],
      "length": 64,
      "volume": 55,
      "pan": 0,
      "muted": false,
      "soloed": false,
      "fx": {
        "reverb": {"enabled": false, "wet": 0.2},
        "delay":  {"enabled": false, "wet": 0.2},
        "distortion": {"enabled": false, "wet": 0.0},
        "filter": {"enabled": true, "frequency": 8000, "type": "highpass"}
      }
    },
    {
      "id": "jb-bell",
      "name": "Grelots",
      "color": "#fbbf24",
      "instrument": "Bell",
      "steps": [false,false,false,false,false,false,false,false,false,false,false,false,false,false,false,false,false,false,false,false,false,false,false,false,false,false,false,false,false,false,false,false,false,false,false,false,false,false,false,false,false,false,false,false,false,false,false,false,false,false,false,false,false,false,false,false,false,false,false,false,false,false,false,false],
      "pianoSteps": [
        {"active":true,"note":"E5"},{"active":false,"note":""},{"active":false,"note":""},{"active":false,"note":""},
        {"active":true,"note":"E5"},{"active":false,"note":""},{"active":false,"note":""},{"active":false,"note":""},
        {"active":true,"note":"E5"},{"active":false,"note":""},{"active":false,"note":""},{"active":false,"note":""},
        {"active":false,"note":""},{"active":false,"note":""},{"active":false,"note":""},{"active":false,"note":""},
        {"active":true,"note":"E5"},{"active":false,"note":""},{"active":false,"note":""},{"active":false,"note":""},
        {"active":true,"note":"E5"},{"active":false,"note":""},{"active":false,"note":""},{"active":false,"note":""},
        {"active":true,"note":"E5"},{"active":false,"note":""},{"active":false,"note":""},{"active":false,"note":""},
        {"active":false,"note":""},{"active":false,"note":""},{"active":false,"note":""},{"active":false,"note":""},
        {"active":true,"note":"G5"},{"active":false,"note":""},{"active":false,"note":""},{"active":false,"note":""},
        {"active":true,"note":"C5"},{"active":false,"note":""},{"active":false,"note":""},{"active":false,"note":""},
        {"active":true,"note":"D5"},{"active":false,"note":""},{"active":false,"note":""},{"active":false,"note":""},
        {"active":true,"note":"E5"},{"active":false,"note":""},{"active":false,"note":""},{"active":false,"note":""},
        {"active":true,"note":"F5"},{"active":false,"note":""},{"active":false,"note":""},{"active":false,"note":""},
        {"active":true,"note":"F5"},{"active":false,"note":""},{"active":false,"note":""},{"active":false,"note":""},
        {"active":true,"note":"G5"},{"active":false,"note":""},{"active":false,"note":""},{"active":false,"note":""},
        {"active":false,"note":""},{"active":false,"note":""},{"active":false,"note":""},{"active":false,"note":""}
      ],
      "length": 64,
      "volume": 45,
      "pan": 0,
      "muted": false,
      "soloed": false,
      "fx": {
        "reverb": {"enabled": true, "wet": 0.4},
        "delay":  {"enabled": true, "wet": 0.25},
        "distortion": {"enabled": false, "wet": 0.0},
        "filter": {"enabled": false, "frequency": 1000, "type": "lowpass"}
      }
    }
  ]
}
